wayland_automation/__init__.py
wayland_automation/__main__.py
wayland_automation/keyboard_controller.py
wayland_automation/mouse_controller.py
wayland_automation/mouse_position.py
wayland_automation/utils/__init__.py
wayland_automation/utils/screen_resolution.py
wayland_automation-0.2.6.dist-info/licenses/LICENCE
wayland_automation-0.2.6.dist-info/METADATA
wayland_automation-0.2.6.dist-info/WHEEL
wayland_automation-0.2.6.dist-info/entry_points.txt
wayland_automation-0.2.6.dist-info/top_level.txt
wayland_automation-0.2.6.dist-info/RECORD
