Metadata-Version: 2.4
Name: wayland_automation
Version: 0.2.6
Summary: A tool for automating Wayland tasks using system packages wtype and wayland-info
Home-page: https://github.com/OTAKUWeBer/Wayland-automation
Author: OTAKUWeBer
Author-email: rtweber2004@gmail.com
Classifier: Programming Language :: Python :: 3
Classifier: Operating System :: POSIX :: Linux
Requires-Python: >=3.6
License-File: LICENCE
Requires-Dist: evdev
Dynamic: author
Dynamic: author-email
Dynamic: classifier
Dynamic: description
Dynamic: description-content-type
Dynamic: home-page
Dynamic: license-file
Dynamic: requires-dist
Dynamic: requires-python
Dynamic: summary
